torch_schedule_anything/__init__.py
torch_schedule_anything/arbitrary_schedules.py
torch_schedule_anything/builtin_schedules.py
torch_schedule_anything/infrastructure.py
torch_schedule_anything/py.typed
torch_schedule_anything-1.2.1.dist-info/licenses/LICENSE
torch_schedule_anything-1.2.1.dist-info/METADATA
torch_schedule_anything-1.2.1.dist-info/WHEEL
torch_schedule_anything-1.2.1.dist-info/top_level.txt
torch_schedule_anything-1.2.1.dist-info/RECORD
