Metadata-Version: 2.4
Name: torch-schedule-anything
Version: 1.2.1
Summary: Schedule any optimizer hyperparameter, not just learning rate
Author-email: Christopher O'Quinn <chrisoquinn.2@gmail.com>
License: MIT
Project-URL: Homepage, https://github.com/smithblack-0/ScheduleAnything
Project-URL: Repository, https://github.com/smithblack-0/ScheduleAnything
Project-URL: Documentation, https://github.com/smithblack-0/ScheduleAnything
Keywords: deep-learning,pytorch,optimization,scheduler,hyperparameter
Classifier: Development Status :: 5 - Production/Stable
Classifier: Intended Audience :: Science/Research
Classifier: License :: OSI Approved :: MIT License
Classifier: Programming Language :: Python :: 3
Classifier: Programming Language :: Python :: 3.9
Classifier: Programming Language :: Python :: 3.10
Classifier: Programming Language :: Python :: 3.11
Classifier: Programming Language :: Python :: 3.12
Classifier: Topic :: Scientific/Engineering :: Artificial Intelligence
Requires-Python: >=3.9
License-File: LICENSE
Requires-Dist: torch>=2.0.0
Provides-Extra: dev
Requires-Dist: pytest>=7.0; extra == "dev"
Requires-Dist: pytest-cov; extra == "dev"
Requires-Dist: black; extra == "dev"
Requires-Dist: ruff; extra == "dev"
Dynamic: license-file
